jasmin_fuzzer/__init__.py
jasmin_fuzzer/jasmin.py
jasmin_fuzzer-0.1.3.dist-info/WHEEL
jasmin_fuzzer-0.1.3.dist-info/METADATA
jasmin_fuzzer-0.1.3.dist-info/LICENSE
jasmin_fuzzer-0.1.3.dist-info/entry_points.txt
jasmin_fuzzer-0.1.3.dist-info/RECORD
